gdscript_docs_maker/__init__.py
gdscript_docs_maker/__main__.py
gdscript_docs_maker/command_line.py
gdscript_docs_maker/config.py
gdscript_docs_maker/convert_to_markdown.py
gdscript_docs_maker/gdscript_objects.py
gdscript_docs_maker/hugo.py
gdscript_docs_maker/make_markdown.py
gdscript_docs_maker/merge_json.py
gdscript_docs_maker/utils.py
gdscript_docs_maker/data/hugo_front_matter.toml
gdscript_docs_maker-1.5.1.data/data/data/hugo_front_matter.toml
gdscript_docs_maker-1.5.1.dist-info/LICENSE
gdscript_docs_maker-1.5.1.dist-info/METADATA
gdscript_docs_maker-1.5.1.dist-info/WHEEL
gdscript_docs_maker-1.5.1.dist-info/top_level.txt
gdscript_docs_maker-1.5.1.dist-info/RECORD
