Metadata-Version: 2.1
Name: gdscript-docs-maker
Version: 1.5.1
Summary: Create documentation and class references from your Godot GDScript code.
Home-page: https://github.com/GDQuest/gdscript-docs-maker
Author: Nathan Lovato
Author-email: nathan@gdquest.com
License: MIT
Keywords: godot,gdscript,documentation,reference,godotengine
Platform: UNKNOWN
Classifier: Development Status :: 5 - Production/Stable
Classifier: Intended Audience :: Developers
Classifier: License :: OSI Approved :: MIT License
Classifier: Programming Language :: Python :: 3
Classifier: Programming Language :: Python :: 3.7
Classifier: Programming Language :: Python :: 3.8
Requires-Python: >=3.7
